tests/__init__.py
tests/test_client.py
tests/test_dispatch.py
tests/test_jsonrpc.py
tests/test_msgpackrpc.py
tests/test_protocols.py
tests/test_rabbitmq_transport.py
tests/test_server.py
tests/test_transport.py
tests/test_wsgi_transport.py
tinyrpc/__init__.py
tinyrpc/client.py
tinyrpc/exc.py
tinyrpc/dispatch/__init__.py
tinyrpc/protocols/__init__.py
tinyrpc/protocols/jsonrpc.py
tinyrpc/protocols/msgpackrpc.py
tinyrpc/server/__init__.py
tinyrpc/server/gevent.py
tinyrpc/transports/__init__.py
tinyrpc/transports/callback.py
tinyrpc/transports/cgi.py
tinyrpc/transports/http.py
tinyrpc/transports/rabbitmq.py
tinyrpc/transports/websocket.py
tinyrpc/transports/websocketclient.py
tinyrpc/transports/wsgi.py
tinyrpc/transports/zmq.py
tinyrpc-1.1.7.dist-info/LICENSE
tinyrpc-1.1.7.dist-info/METADATA
tinyrpc-1.1.7.dist-info/WHEEL
tinyrpc-1.1.7.dist-info/top_level.txt
tinyrpc-1.1.7.dist-info/RECORD
