Metadata-Version: 2.1
Name: tinyrpc
Version: 1.1.7
Summary: A small, modular, transport and protocol neutral RPC library that, among other things, supports JSON-RPC and zmq.
Home-page: http://github.com/mbr/tinyrpc
Author: Marc Brinkmann
Author-email: git@marcbrinkmann.de
Maintainer: Leo Noordergraaf
Maintainer-email: leo@noordergraaf.net
License: MIT
Keywords: json rpc json-rpc jsonrpc 0mq zmq zeromq
Provides-Extra: gevent
Provides-Extra: httpclient
Provides-Extra: msgpack
Provides-Extra: websocket
Provides-Extra: wsgi
Provides-Extra: zmq
Provides-Extra: jsonext
Provides-Extra: rabbitmq
License-File: LICENSE
